vcf2bedgraph/__about__.py
vcf2bedgraph/__init__.py
vcf2bedgraph/cli.py
vcf2bedgraph-0.1.5.dist-info/METADATA
vcf2bedgraph-0.1.5.dist-info/WHEEL
vcf2bedgraph-0.1.5.dist-info/entry_points.txt
vcf2bedgraph-0.1.5.dist-info/licenses/LICENSE
vcf2bedgraph-0.1.5.dist-info/RECORD
