Metadata-Version: 2.4
Name: vcf2bedgraph
Version: 0.1.5
Summary: Convert VCF files to BedGraph format
Project-URL: Homepage, https://github.com/fcliquet/vcf2bedgraph
Project-URL: Repository, https://github.com/fcliquet/vcf2bedgraph.git
Project-URL: Issues, https://github.com/fcliquet/vcf2bedgraph/issues
Author-email: Your Name <your.email@example.com>
License: MIT
License-File: LICENSE
Keywords: bedgraph,bioinformatics,genomics,vcf
Classifier: Development Status :: 3 - Alpha
Classifier: Intended Audience :: Science/Research
Classifier: License :: OSI Approved :: MIT License
Classifier: Programming Language :: Python :: 3
Classifier: Programming Language :: Python :: 3.8
Classifier: Programming Language :: Python :: 3.9
Classifier: Programming Language :: Python :: 3.10
Classifier: Programming Language :: Python :: 3.11
Classifier: Programming Language :: Python :: 3.12
Requires-Python: >=3.8
Requires-Dist: cyvcf2>=0.30.0
Requires-Dist: pysam>=0.19.0
